odoo/addons/ssi_hr_recruitment_career_transition/README.rst
odoo/addons/ssi_hr_recruitment_career_transition/__init__.py
odoo/addons/ssi_hr_recruitment_career_transition/__manifest__.py
odoo/addons/ssi_hr_recruitment_career_transition/models/__init__.py
odoo/addons/ssi_hr_recruitment_career_transition/models/recruitment_applicant.py
odoo/addons/ssi_hr_recruitment_career_transition/static/description/icon.png
odoo/addons/ssi_hr_recruitment_career_transition/views/recruitment_applicant_views.xml
odoo14_addon_ssi_hr_recruitment_career_transition-14.0.1.0.0.dist-info/METADATA
odoo14_addon_ssi_hr_recruitment_career_transition-14.0.1.0.0.dist-info/WHEEL
odoo14_addon_ssi_hr_recruitment_career_transition-14.0.1.0.0.dist-info/top_level.txt
odoo14_addon_ssi_hr_recruitment_career_transition-14.0.1.0.0.dist-info/RECORD
